README.md
setup.cfg
setup.py
beeminderpy/__init__.py
beeminderpy/client.py
beeminderpy.egg-info/PKG-INFO
beeminderpy.egg-info/SOURCES.txt
beeminderpy.egg-info/dependency_links.txt
beeminderpy.egg-info/entry_points.txt
beeminderpy.egg-info/requires.txt
beeminderpy.egg-info/top_level.txt
beeminderpy/cli/__init__.py
beeminderpy/cli/cli.py