Metadata-Version: 1.2
Name: beeminderpy
Version: 0.0.3
Summary: Python async wrapper for the Beeminder REST API
Home-page: https://github.com/b1r3k/beeminderpy/
Author: Lukasz Jachym
Author-email: lukasz.jachym@gmail.com
License: MIT
Platform: UNKNOWN
Classifier: License :: OSI Approved :: MIT License
Classifier: Intended Audience :: Developers
Classifier: Programming Language :: Python
Classifier: Programming Language :: Python :: 3
Classifier: Programming Language :: Python :: 3.6
Classifier: Programming Language :: Python :: 3.7
Classifier: Topic :: Internet :: WWW/HTTP
Classifier: Framework :: AsyncIO
Requires-Python: >=3.6
